sqlmapper.py
PythonSQLMapper-1.2.dist-info/LICENSE
PythonSQLMapper-1.2.dist-info/METADATA
PythonSQLMapper-1.2.dist-info/WHEEL
PythonSQLMapper-1.2.dist-info/top_level.txt
PythonSQLMapper-1.2.dist-info/RECORD
