Metadata-Version: 2.1
Name: PythonSQLMapper
Version: 1.2
Summary: SQL mapping library for python.
Home-page: https://github.com/marvelph/PythonSQLMapper
Author: Kenji Nishishiro
Author-email: marvel@programmershigh.org
License: MIT
Platform: any
Classifier: Development Status :: 5 - Production/Stable
Classifier: Intended Audience :: Developers
Classifier: License :: OSI Approved :: MIT License
Classifier: Operating System :: OS Independent
Classifier: Programming Language :: Python :: 3
Classifier: Programming Language :: Python :: 3.5
Requires-Python: >=3.5
License-File: LICENSE
